model_validation/__init__.py
model_validation/validation.py
model_validation-0.2.dist-info/LICENSE.txt
model_validation-0.2.dist-info/METADATA
model_validation-0.2.dist-info/WHEEL
model_validation-0.2.dist-info/top_level.txt
model_validation-0.2.dist-info/RECORD
