Metadata-Version: 2.1
Name: model-validation
Version: 0.2
Summary: Model validation tools
Home-page: http://github.com/Alexandre-Papandrea/model_validation
Author: Alexandre Papandrea
Author-email: alexandre@dadosinteligentes.com
Classifier: Programming Language :: Python :: 3
Classifier: License :: OSI Approved :: MIT License
Classifier: Operating System :: OS Independent
Requires-Python: >=3.6
License-File: LICENSE.txt
Requires-Dist: ipywidgets
Requires-Dist: pandas
Requires-Dist: numpy
Requires-Dist: plotly
Requires-Dist: scikit-learn
Requires-Dist: scipy
Requires-Dist: statsmodels
